xtdb/__init__.py
xtdb/__main__.py
xtdb/datalog.py
xtdb/exceptions.py
xtdb/orm.py
xtdb/query.py
xtdb/session.py
xtdb-0.6.2.dist-info/LICENSE
xtdb-0.6.2.dist-info/METADATA
xtdb-0.6.2.dist-info/WHEEL
xtdb-0.6.2.dist-info/RECORD
