Metadata-Version: 2.1
Name: xtdb
Version: 0.6.2
Summary: A Python ORM for XTDB.
Home-page: https://github.com/Donnype/xtdb-py
Author: Donny Peeters
Author-email: donny.peeters@hotmail.com
Maintainer: Donny Peeters
Maintainer-email: donny.peeters@hotmail.com
Requires-Python: >=3.8,<4.0
Classifier: Programming Language :: Python :: 3
Classifier: Programming Language :: Python :: 3.8
Classifier: Programming Language :: Python :: 3.9
Classifier: Programming Language :: Python :: 3.10
Classifier: Programming Language :: Python :: 3.11
Classifier: Programming Language :: Python :: 3.12
Requires-Dist: requests (>=2.26.0,<3.0.0)
Project-URL: Repository, https://github.com/Donnype/xtdb-py
